katachi/__init__.py
katachi/__main__.py
katachi/cli.py
katachi/schema/__init__.py
katachi/schema/actions.py
katachi/schema/importer.py
katachi/schema/schema_node.py
katachi/validation/__init__.py
katachi/validation/core.py
katachi/validation/registry.py
katachi/validation/validators.py
katachi-0.0.5a0.dist-info/METADATA
katachi-0.0.5a0.dist-info/WHEEL
katachi-0.0.5a0.dist-info/entry_points.txt
katachi-0.0.5a0.dist-info/licenses/LICENSE
katachi-0.0.5a0.dist-info/RECORD
