Metadata-Version: 2.4
Name: katachi
Version: 0.0.5a0
Summary: Python package for validating, processing and parsing directories.
Project-URL: Homepage, https://nmicovic.github.io/katachi/
Project-URL: Repository, https://github.com/nmicovic/katachi
Project-URL: Documentation, https://nmicovic.github.io/katachi/
Author-email: Nemanja Micovic <contact.nmicovic@protonmail.com>
License-File: LICENSE
Keywords: python
Classifier: Intended Audience :: Developers
Classifier: Programming Language :: Python
Classifier: Programming Language :: Python :: 3
Classifier: Programming Language :: Python :: 3.9
Classifier: Programming Language :: Python :: 3.10
Classifier: Programming Language :: Python :: 3.11
Classifier: Programming Language :: Python :: 3.12
Classifier: Programming Language :: Python :: 3.13
Classifier: Topic :: Software Development :: Libraries :: Python Modules
Requires-Python: <4.0,>=3.9
Requires-Dist: pyyaml>=6.0.2
Requires-Dist: rich>=14.0.0
Requires-Dist: typer>=0.15.3
